FireWrap/__init__.py
FireWrap/blueprint.py
FireWrap/fire.py
FireWrap/port.py
FireWrap/utils.py
firewrap-0.1.7.4.dist-info/METADATA
firewrap-0.1.7.4.dist-info/WHEEL
firewrap-0.1.7.4.dist-info/top_level.txt
firewrap-0.1.7.4.dist-info/RECORD
