Metadata-Version: 2.1
Name: firewrap
Version: 0.1.7.4
Summary: A Firestore-like wrapper for SQL databases.
Author: Muhammad Saboor Islam
Author-email: muhammadsaboor119@gmail.com
Classifier: Development Status :: 3 - Alpha
Classifier: Intended Audience :: Developers
Classifier: License :: OSI Approved :: MIT License
Classifier: Programming Language :: Python :: 3
Classifier: Programming Language :: Python :: 3.7
Classifier: Programming Language :: Python :: 3.8
Classifier: Programming Language :: Python :: 3.9
Requires-Python: >=3.6
Requires-Dist: dataset
Requires-Dist: dotty-dict
Requires-Dist: flask
